cmsplugin_filer_album
