Metadata-Version: 1.0
Name: cmsplugin-filer-album
Version: 0.0.3
Summary: DjangoCMS filer plugin for show albums with template selection
Home-page: http://bitbucket.org/ffaxl/cmsplugin-imagealbum
Author: Eugene Slizevich
Author-email: eugene@slizevich.net
License: GPL
Keywords: django-cms filer plugin album template
Platform: UNKNOWN
